spotipy_cli
